immutable_views/__init__.py
immutable_views/_dict_view.py
immutable_views/_list_view.py
immutable_views/_set_view.py
immutable_views/_version.py
immutable_views-0.6.1.dist-info/LICENSE
immutable_views-0.6.1.dist-info/METADATA
immutable_views-0.6.1.dist-info/WHEEL
immutable_views-0.6.1.dist-info/top_level.txt
immutable_views-0.6.1.dist-info/zip-safe
immutable_views-0.6.1.dist-info/RECORD
